[
  {
    "name": "garden",
    "trans": [],
    "usphone": "",
    "ukphone": ""
  },
  {
    "name": "sandpit",
    "trans": [],
    "usphone": "",
    "ukphone": ""
  },
  {
    "name": "bumble-bee",
    "trans": [],
    "usphone": "",
    "ukphone": ""
  },
  {
    "name": "mountain",
    "trans": [],
    "usphone": "",
    "ukphone": ""
  },
  {
    "name": "flowerpot",
    "trans": [],
    "usphone": "",
    "ukphone": ""
  },
  {
    "name": "mend",
    "trans": [],
    "usphone": "",
    "ukphone": ""
  },
  {
    "name": "bandage",
    "trans": [],
    "usphone": "",
    "ukphone": ""
  },
  {
    "name": "apatosaurus",
    "trans": [],
    "usphone": "",
    "ukphone": ""
  },
  {
    "name": "dragonfly",
    "trans": [],
    "usphone": "",
    "ukphone": ""
  },
  {
    "name": "footprint",
    "trans": [],
    "usphone": "",
    "ukphone": ""
  },
  {
    "name": "crack",
    "trans": [],
    "usphone": "",
    "ukphone": ""
  },
  {
    "name": "pantomine",
    "trans": [],
    "usphone": "",
    "ukphone": ""
  },
  {
    "name": "sheriff",
    "trans": [],
    "usphone": "",
    "ukphone": ""
  },
  {
    "name": "grab",
    "trans": [],
    "usphone": "",
    "ukphone": ""
  },
  {
    "name": "pot",
    "trans": [],
    "usphone": "",
    "ukphone": ""
  },
  {
    "name": "chest",
    "trans": [],
    "usphone": "",
    "ukphone": ""
  },
  {
    "name": "brick",
    "trans": [],
    "usphone": "",
    "ukphone": ""
  },
  {
    "name": "fish tank",
    "trans": [],
    "usphone": "",
    "ukphone": ""
  },
  {
    "name": "ship",
    "trans": [],
    "usphone": "",
    "ukphone": ""
  },
  {
    "name": "rock",
    "trans": [],
    "usphone": "",
    "ukphone": ""
  },
  {
    "name": "underwater",
    "trans": [],
    "usphone": "",
    "ukphone": ""
  },
  {
    "name": "mask",
    "trans": [],
    "usphone": "",
    "ukphone": ""
  },
  {
    "name": "plastic bag",
    "trans": [],
    "usphone": "",
    "ukphone": ""
  },
  {
    "name": "fireplace",
    "trans": [],
    "usphone": "",
    "ukphone": ""
  },
  {
    "name": "light the fire",
    "trans": [],
    "usphone": "",
    "ukphone": ""
  },
  {
    "name": "ghost",
    "trans": [],
    "usphone": "",
    "ukphone": ""
  },
  {
    "name": "toast",
    "trans": [],
    "usphone": "",
    "ukphone": ""
  },
  {
    "name": "rotten apples",
    "trans": [],
    "usphone": "",
    "ukphone": ""
  },
  {
    "name": "dustbin",
    "trans": [],
    "usphone": "",
    "ukphone": ""
  },
  {
    "name": "empty",
    "trans": [],
    "usphone": "",
    "ukphone": ""
  },
  {
    "name": "wig",
    "trans": [],
    "usphone": "",
    "ukphone": ""
  },
  {
    "name": "cushion",
    "trans": [],
    "usphone": "",
    "ukphone": ""
  },
  {
    "name": "Christmas Eve",
    "trans": [],
    "usphone": "",
    "ukphone": ""
  },
  {
    "name": "decoration",
    "trans": [],
    "usphone": "",
    "ukphone": ""
  },
  {
    "name": "turn off",
    "trans": [],
    "usphone": "",
    "ukphone": ""
  },
  {
    "name": "programme",
    "trans": [],
    "usphone": "",
    "ukphone": ""
  },
  {
    "name": "Father Christmas",
    "trans": [],
    "usphone": "",
    "ukphone": ""
  },
  {
    "name": "door bell",
    "trans": [],
    "usphone": "",
    "ukphone": ""
  },
  {
    "name": "disappointed",
    "trans": [],
    "usphone": "",
    "ukphone": ""
  },
  {
    "name": "strawberry jam sandwiches",
    "trans": [],
    "usphone": "",
    "ukphone": ""
  },
  {
    "name": "lemonade",
    "trans": [],
    "usphone": "",
    "ukphone": ""
  },
  {
    "name": "cracker",
    "trans": [],
    "usphone": "",
    "ukphone": ""
  },
  {
    "name": "notice",
    "trans": [],
    "usphone": "",
    "ukphone": ""
  },
  {
    "name": "shed",
    "trans": [],
    "usphone": "",
    "ukphone": ""
  },
  {
    "name": "brilliant",
    "trans": [],
    "usphone": "",
    "ukphone": ""
  },
  {
    "name": "bent",
    "trans": [],
    "usphone": "",
    "ukphone": ""
  },
  {
    "name": "armchair",
    "trans": [],
    "usphone": "",
    "ukphone": ""
  },
  {
    "name": "ear-ring",
    "trans": [],
    "usphone": "",
    "ukphone": ""
  },
  {
    "name": "shiny",
    "trans": [],
    "usphone": "",
    "ukphone": ""
  },
  {
    "name": "bright",
    "trans": [],
    "usphone": "",
    "ukphone": ""
  },
  {
    "name": "gloomy",
    "trans": [],
    "usphone": "",
    "ukphone": ""
  },
  {
    "name": "prison",
    "trans": [],
    "usphone": "",
    "ukphone": ""
  },
  {
    "name": "magpie",
    "trans": [],
    "usphone": "",
    "ukphone": ""
  },
  {
    "name": "crossly",
    "trans": [],
    "usphone": "",
    "ukphone": ""
  },
  {
    "name": "medal",
    "trans": [],
    "usphone": "",
    "ukphone": ""
  },
  {
    "name": "Paris",
    "trans": [],
    "usphone": "",
    "ukphone": ""
  },
  {
    "name": "Eiffel Tower",
    "trans": [],
    "usphone": "",
    "ukphone": ""
  },
  {
    "name": "French flag",
    "trans": [],
    "usphone": "",
    "ukphone": ""
  },
  {
    "name": "cart",
    "trans": [],
    "usphone": "",
    "ukphone": ""
  },
  {
    "name": "hall",
    "trans": [],
    "usphone": "",
    "ukphone": ""
  },
  {
    "name": "torch",
    "trans": [],
    "usphone": "",
    "ukphone": ""
  },
  {
    "name": "glass bead",
    "trans": [],
    "usphone": "",
    "ukphone": ""
  },
  {
    "name": "magnifying glass",
    "trans": [],
    "usphone": "",
    "ukphone": ""
  },
  {
    "name": "throne",
    "trans": [],
    "usphone": "",
    "ukphone": ""
  },
  {
    "name": "stairs",
    "trans": [],
    "usphone": "",
    "ukphone": ""
  },
  {
    "name": "guard",
    "trans": [],
    "usphone": "",
    "ukphone": ""
  },
  {
    "name": "crown",
    "trans": [],
    "usphone": "",
    "ukphone": ""
  },
  {
    "name": "arrow",
    "trans": [],
    "usphone": "",
    "ukphone": ""
  },
  {
    "name": "bead",
    "trans": [],
    "usphone": "",
    "ukphone": ""
  },
  {
    "name": "zip wire",
    "trans": [],
    "usphone": "",
    "ukphone": ""
  },
  {
    "name": "cliff",
    "trans": [],
    "usphone": "",
    "ukphone": ""
  },
  {
    "name": "crutch",
    "trans": [],
    "usphone": "",
    "ukphone": ""
  },
  {
    "name": "lifeboat",
    "trans": [],
    "usphone": "",
    "ukphone": ""
  },
  {
    "name": "pole",
    "trans": [],
    "usphone": "",
    "ukphone": ""
  },
  {
    "name": "cannon",
    "trans": [],
    "usphone": "",
    "ukphone": ""
  },
  {
    "name": "donkey",
    "trans": [],
    "usphone": "",
    "ukphone": ""
  },
  {
    "name": "pulley",
    "trans": [],
    "usphone": "",
    "ukphone": ""
  },
  {
    "name": "sunbed",
    "trans": [],
    "usphone": "",
    "ukphone": ""
  },
  {
    "name": "nature laboratory",
    "trans": [],
    "usphone": "",
    "ukphone": ""
  },
  {
    "name": "leaves",
    "trans": [],
    "usphone": "",
    "ukphone": ""
  },
  {
    "name": "bark rubbing",
    "trans": [],
    "usphone": "",
    "ukphone": ""
  },
  {
    "name": "stuck",
    "trans": [],
    "usphone": "",
    "ukphone": ""
  },
  {
    "name": "seed",
    "trans": [],
    "usphone": "",
    "ukphone": ""
  },
  {
    "name": "pot",
    "trans": [],
    "usphone": "",
    "ukphone": ""
  },
  {
    "name": "mushrooms",
    "trans": [],
    "usphone": "",
    "ukphone": ""
  },
  {
    "name": "paste",
    "trans": [],
    "usphone": "",
    "ukphone": ""
  },
  {
    "name": "cast",
    "trans": [],
    "usphone": "",
    "ukphone": ""
  },
  {
    "name": "animal track",
    "trans": [],
    "usphone": "",
    "ukphone": ""
  },
  {
    "name": "shooting stars",
    "trans": [],
    "usphone": "",
    "ukphone": ""
  },
  {
    "name": "Olympic Games",
    "trans": [],
    "usphone": "",
    "ukphone": ""
  },
  {
    "name": "olive tree",
    "trans": [],
    "usphone": "",
    "ukphone": ""
  },
  {
    "name": "villager",
    "trans": [],
    "usphone": "",
    "ukphone": ""
  },
  {
    "name": "male",
    "trans": [],
    "usphone": "",
    "ukphone": ""
  },
  {
    "name": "sewing",
    "trans": [],
    "usphone": "",
    "ukphone": ""
  },
  {
    "name": "shield",
    "trans": [],
    "usphone": "",
    "ukphone": ""
  },
  {
    "name": "prize",
    "trans": [],
    "usphone": "",
    "ukphone": ""
  },
  {
    "name": "vase",
    "trans": [],
    "usphone": "",
    "ukphone": ""
  },
  {
    "name": "disc",
    "trans": [],
    "usphone": "",
    "ukphone": ""
  },
  {
    "name": "three legged",
    "trans": [],
    "usphone": "",
    "ukphone": ""
  },
  {
    "name": "olive-and-spoon race",
    "trans": [],
    "usphone": "",
    "ukphone": ""
  },
  {
    "name": "slip",
    "trans": [],
    "usphone": "",
    "ukphone": ""
  },
  {
    "name": "family meeting",
    "trans": [],
    "usphone": "",
    "ukphone": ""
  },
  {
    "name": "middle",
    "trans": [],
    "usphone": "",
    "ukphone": ""
  },
  {
    "name": "rack",
    "trans": [],
    "usphone": "",
    "ukphone": ""
  },
  {
    "name": "hedge",
    "trans": [],
    "usphone": "",
    "ukphone": ""
  },
  {
    "name": "cottage",
    "trans": [],
    "usphone": "",
    "ukphone": ""
  },
  {
    "name": "chimney",
    "trans": [],
    "usphone": "",
    "ukphone": ""
  },
  {
    "name": "crow",
    "trans": [],
    "usphone": "",
    "ukphone": ""
  },
  {
    "name": "let it out",
    "trans": [],
    "usphone": "",
    "ukphone": ""
  },
  {
    "name": "pattern",
    "trans": [],
    "usphone": "",
    "ukphone": ""
  },
  {
    "name": "mirror",
    "trans": [],
    "usphone": "",
    "ukphone": ""
  },
  {
    "name": "island",
    "trans": [],
    "usphone": "",
    "ukphone": ""
  },
  {
    "name": "spade",
    "trans": [],
    "usphone": "",
    "ukphone": ""
  },
  {
    "name": "plastic snake",
    "trans": [],
    "usphone": "",
    "ukphone": ""
  },
  {
    "name": "addition sums",
    "trans": [],
    "usphone": "",
    "ukphone": ""
  },
  {
    "name": "gander",
    "trans": [],
    "usphone": "",
    "ukphone": ""
  },
  {
    "name": "peck",
    "trans": [],
    "usphone": "",
    "ukphone": ""
  },
  {
    "name": "bottom",
    "trans": [],
    "usphone": "",
    "ukphone": ""
  },
  {
    "name": "gooseberries",
    "trans": [],
    "usphone": "",
    "ukphone": ""
  }
]