[
  {
    "name": "aeroplane",
    "trans": [],
    "usphone": "",
    "ukphone": ""
  },
  {
    "name": "afraid",
    "trans": [],
    "usphone": "",
    "ukphone": ""
  },
  {
    "name": "angry",
    "trans": [],
    "usphone": "",
    "ukphone": ""
  },
  {
    "name": "arm",
    "trans": [],
    "usphone": "",
    "ukphone": ""
  },
  {
    "name": "autumn",
    "trans": [],
    "usphone": "",
    "ukphone": ""
  },
  {
    "name": "bad",
    "trans": [],
    "usphone": "",
    "ukphone": ""
  },
  {
    "name": "bag",
    "trans": [],
    "usphone": "",
    "ukphone": ""
  },
  {
    "name": "beach",
    "trans": [],
    "usphone": "",
    "ukphone": ""
  },
  {
    "name": "bitter",
    "trans": [],
    "usphone": "",
    "ukphone": ""
  },
  {
    "name": "body",
    "trans": [],
    "usphone": "",
    "ukphone": ""
  },
  {
    "name": "boil",
    "trans": [],
    "usphone": "",
    "ukphone": ""
  },
  {
    "name": "bread",
    "trans": [],
    "usphone": "",
    "ukphone": ""
  },
  {
    "name": "bus",
    "trans": [],
    "usphone": "",
    "ukphone": ""
  },
  {
    "name": "busy",
    "trans": [],
    "usphone": "",
    "ukphone": ""
  },
  {
    "name": "by",
    "trans": [],
    "usphone": "",
    "ukphone": ""
  },
  {
    "name": "car",
    "trans": [],
    "usphone": "",
    "ukphone": ""
  },
  {
    "name": "chair",
    "trans": [],
    "usphone": "",
    "ukphone": ""
  },
  {
    "name": "children",
    "trans": [],
    "usphone": "",
    "ukphone": ""
  },
  {
    "name": "Children's Day",
    "trans": [],
    "usphone": "",
    "ukphone": ""
  },
  {
    "name": "China",
    "trans": [],
    "usphone": "",
    "ukphone": ""
  },
  {
    "name": "cinema",
    "trans": [],
    "usphone": "",
    "ukphone": ""
  },
  {
    "name": "circle",
    "trans": [],
    "usphone": "",
    "ukphone": ""
  },
  {
    "name": "clever",
    "trans": [],
    "usphone": "",
    "ukphone": ""
  },
  {
    "name": "clock",
    "trans": [],
    "usphone": "",
    "ukphone": ""
  },
  {
    "name": "clothes",
    "trans": [],
    "usphone": "",
    "ukphone": ""
  },
  {
    "name": "coffee",
    "trans": [],
    "usphone": "",
    "ukphone": ""
  },
  {
    "name": "cold",
    "trans": [],
    "usphone": "",
    "ukphone": ""
  },
  {
    "name": "do",
    "trans": [],
    "usphone": "",
    "ukphone": ""
  },
  {
    "name": "does",
    "trans": [],
    "usphone": "",
    "ukphone": ""
  },
  {
    "name": "doll",
    "trans": [],
    "usphone": "",
    "ukphone": ""
  },
  {
    "name": "easy",
    "trans": [],
    "usphone": "",
    "ukphone": ""
  },
  {
    "name": "elephant",
    "trans": [],
    "usphone": "",
    "ukphone": ""
  },
  {
    "name": "else",
    "trans": [],
    "usphone": "",
    "ukphone": ""
  },
  {
    "name": "English",
    "trans": [],
    "usphone": "",
    "ukphone": ""
  },
  {
    "name": "fifth",
    "trans": [],
    "usphone": "",
    "ukphone": ""
  },
  {
    "name": "finally",
    "trans": [],
    "usphone": "",
    "ukphone": ""
  },
  {
    "name": "finger",
    "trans": [],
    "usphone": "",
    "ukphone": ""
  },
  {
    "name": "first",
    "trans": [],
    "usphone": "",
    "ukphone": ""
  },
  {
    "name": "food",
    "trans": [],
    "usphone": "",
    "ukphone": ""
  },
  {
    "name": "foot",
    "trans": [],
    "usphone": "",
    "ukphone": ""
  },
  {
    "name": "for",
    "trans": [],
    "usphone": "",
    "ukphone": ""
  },
  {
    "name": "fourteenth",
    "trans": [],
    "usphone": "",
    "ukphone": ""
  },
  {
    "name": "fruit",
    "trans": [],
    "usphone": "",
    "ukphone": ""
  },
  {
    "name": "fun",
    "trans": [],
    "usphone": "",
    "ukphone": ""
  },
  {
    "name": "funny",
    "trans": [],
    "usphone": "",
    "ukphone": ""
  },
  {
    "name": "glass",
    "trans": [],
    "usphone": "",
    "ukphone": ""
  },
  {
    "name": "glove",
    "trans": [],
    "usphone": "",
    "ukphone": ""
  },
  {
    "name": "go away",
    "trans": [],
    "usphone": "",
    "ukphone": ""
  },
  {
    "name": "go fishing",
    "trans": [],
    "usphone": "",
    "ukphone": ""
  },
  {
    "name": "grass",
    "trans": [],
    "usphone": "",
    "ukphone": ""
  },
  {
    "name": "grasshopper",
    "trans": [],
    "usphone": "",
    "ukphone": ""
  },
  {
    "name": "great",
    "trans": [],
    "usphone": "",
    "ukphone": ""
  },
  {
    "name": "hard",
    "trans": [],
    "usphone": "",
    "ukphone": ""
  },
  {
    "name": "has",
    "trans": [],
    "usphone": "",
    "ukphone": ""
  },
  {
    "name": "hat",
    "trans": [],
    "usphone": "",
    "ukphone": ""
  },
  {
    "name": "head",
    "trans": [],
    "usphone": "",
    "ukphone": ""
  },
  {
    "name": "hear",
    "trans": [],
    "usphone": "",
    "ukphone": ""
  },
  {
    "name": "help",
    "trans": [],
    "usphone": "",
    "ukphone": ""
  },
  {
    "name": "his",
    "trans": [],
    "usphone": "",
    "ukphone": ""
  },
  {
    "name": "home",
    "trans": [],
    "usphone": "",
    "ukphone": ""
  },
  {
    "name": "horse",
    "trans": [],
    "usphone": "",
    "ukphone": ""
  },
  {
    "name": "house",
    "trans": [],
    "usphone": "",
    "ukphone": ""
  },
  {
    "name": "how",
    "trans": [],
    "usphone": "",
    "ukphone": ""
  },
  {
    "name": "hungry",
    "trans": [],
    "usphone": "",
    "ukphone": ""
  },
  {
    "name": "ice-skate",
    "trans": [],
    "usphone": "",
    "ukphone": ""
  },
  {
    "name": "into",
    "trans": [],
    "usphone": "",
    "ukphone": ""
  },
  {
    "name": "jacket",
    "trans": [],
    "usphone": "",
    "ukphone": ""
  },
  {
    "name": "January",
    "trans": [],
    "usphone": "",
    "ukphone": ""
  },
  {
    "name": "Japan",
    "trans": [],
    "usphone": "",
    "ukphone": ""
  },
  {
    "name": "July",
    "trans": [],
    "usphone": "",
    "ukphone": ""
  },
  {
    "name": "jump",
    "trans": [],
    "usphone": "",
    "ukphone": ""
  },
  {
    "name": "June",
    "trans": [],
    "usphone": "",
    "ukphone": ""
  },
  {
    "name": "knee",
    "trans": [],
    "usphone": "",
    "ukphone": ""
  },
  {
    "name": "leg",
    "trans": [],
    "usphone": "",
    "ukphone": ""
  },
  {
    "name": "lemon",
    "trans": [],
    "usphone": "",
    "ukphone": ""
  },
  {
    "name": "lion",
    "trans": [],
    "usphone": "",
    "ukphone": ""
  },
  {
    "name": "listen",
    "trans": [],
    "usphone": "",
    "ukphone": ""
  },
  {
    "name": "lovely",
    "trans": [],
    "usphone": "",
    "ukphone": ""
  },
  {
    "name": "make",
    "trans": [],
    "usphone": "",
    "ukphone": ""
  },
  {
    "name": "March",
    "trans": [],
    "usphone": "",
    "ukphone": ""
  },
  {
    "name": "monkey",
    "trans": [],
    "usphone": "",
    "ukphone": ""
  },
  {
    "name": "moon",
    "trans": [],
    "usphone": "",
    "ukphone": ""
  },
  {
    "name": "mountain",
    "trans": [],
    "usphone": "",
    "ukphone": ""
  },
  {
    "name": "myself",
    "trans": [],
    "usphone": "",
    "ukphone": ""
  },
  {
    "name": "October",
    "trans": [],
    "usphone": "",
    "ukphone": ""
  },
  {
    "name": "on",
    "trans": [],
    "usphone": "",
    "ukphone": ""
  },
  {
    "name": "outside",
    "trans": [],
    "usphone": "",
    "ukphone": ""
  },
  {
    "name": "over there",
    "trans": [],
    "usphone": "",
    "ukphone": ""
  },
  {
    "name": "own",
    "trans": [],
    "usphone": "",
    "ukphone": ""
  },
  {
    "name": "pair",
    "trans": [],
    "usphone": "",
    "ukphone": ""
  },
  {
    "name": "a pair of",
    "trans": [],
    "usphone": "",
    "ukphone": ""
  },
  {
    "name": "panda",
    "trans": [],
    "usphone": "",
    "ukphone": ""
  },
  {
    "name": "parent",
    "trans": [],
    "usphone": "",
    "ukphone": ""
  },
  {
    "name": "photograph",
    "trans": [],
    "usphone": "",
    "ukphone": ""
  },
  {
    "name": "picnic",
    "trans": [],
    "usphone": "",
    "ukphone": ""
  },
  {
    "name": "pie",
    "trans": [],
    "usphone": "",
    "ukphone": ""
  },
  {
    "name": "pineapple",
    "trans": [],
    "usphone": "",
    "ukphone": ""
  },
  {
    "name": "play",
    "trans": [],
    "usphone": "",
    "ukphone": ""
  },
  {
    "name": "rectangle",
    "trans": [],
    "usphone": "",
    "ukphone": ""
  },
  {
    "name": "river",
    "trans": [],
    "usphone": "",
    "ukphone": ""
  },
  {
    "name": "robot",
    "trans": [],
    "usphone": "",
    "ukphone": ""
  },
  {
    "name": "rock",
    "trans": [],
    "usphone": "",
    "ukphone": ""
  },
  {
    "name": "rough",
    "trans": [],
    "usphone": "",
    "ukphone": ""
  },
  {
    "name": "salt",
    "trans": [],
    "usphone": "",
    "ukphone": ""
  },
  {
    "name": "salty",
    "trans": [],
    "usphone": "",
    "ukphone": ""
  },
  {
    "name": "sandcastle",
    "trans": [],
    "usphone": "",
    "ukphone": ""
  },
  {
    "name": "Saturday",
    "trans": [],
    "usphone": "",
    "ukphone": ""
  },
  {
    "name": "scarf",
    "trans": [],
    "usphone": "",
    "ukphone": ""
  },
  {
    "name": "sea",
    "trans": [],
    "usphone": "",
    "ukphone": ""
  },
  {
    "name": "season",
    "trans": [],
    "usphone": "",
    "ukphone": ""
  },
  {
    "name": "second",
    "trans": [],
    "usphone": "",
    "ukphone": ""
  },
  {
    "name": "shape",
    "trans": [],
    "usphone": "",
    "ukphone": ""
  },
  {
    "name": "ship",
    "trans": [],
    "usphone": "",
    "ukphone": ""
  },
  {
    "name": "shoulder",
    "trans": [],
    "usphone": "",
    "ukphone": ""
  },
  {
    "name": "Singapore",
    "trans": [],
    "usphone": "",
    "ukphone": ""
  },
  {
    "name": "skateboard",
    "trans": [],
    "usphone": "",
    "ukphone": ""
  },
  {
    "name": "ski",
    "trans": [],
    "usphone": "",
    "ukphone": ""
  },
  {
    "name": "sky",
    "trans": [],
    "usphone": "",
    "ukphone": ""
  },
  {
    "name": "sleep",
    "trans": [],
    "usphone": "",
    "ukphone": ""
  },
  {
    "name": "slowly",
    "trans": [],
    "usphone": "",
    "ukphone": ""
  },
  {
    "name": "smell",
    "trans": [],
    "usphone": "",
    "ukphone": ""
  },
  {
    "name": "smooth",
    "trans": [],
    "usphone": "",
    "ukphone": ""
  },
  {
    "name": "snow",
    "trans": [],
    "usphone": "",
    "ukphone": ""
  },
  {
    "name": "so",
    "trans": [],
    "usphone": "",
    "ukphone": ""
  },
  {
    "name": "sock",
    "trans": [],
    "usphone": "",
    "ukphone": ""
  },
  {
    "name": "soft",
    "trans": [],
    "usphone": "",
    "ukphone": ""
  },
  {
    "name": "song",
    "trans": [],
    "usphone": "",
    "ukphone": ""
  },
  {
    "name": "sour",
    "trans": [],
    "usphone": "",
    "ukphone": ""
  },
  {
    "name": "spring",
    "trans": [],
    "usphone": "",
    "ukphone": ""
  },
  {
    "name": "square",
    "trans": [],
    "usphone": "",
    "ukphone": ""
  },
  {
    "name": "star",
    "trans": [],
    "usphone": "",
    "ukphone": ""
  },
  {
    "name": "stop",
    "trans": [],
    "usphone": "",
    "ukphone": ""
  },
  {
    "name": "story",
    "trans": [],
    "usphone": "",
    "ukphone": ""
  },
  {
    "name": "strong",
    "trans": [],
    "usphone": "",
    "ukphone": ""
  },
  {
    "name": "summer",
    "trans": [],
    "usphone": "",
    "ukphone": ""
  },
  {
    "name": "super",
    "trans": [],
    "usphone": "",
    "ukphone": ""
  },
  {
    "name": "sweet",
    "trans": [],
    "usphone": "",
    "ukphone": ""
  },
  {
    "name": "take",
    "trans": [],
    "usphone": "",
    "ukphone": ""
  },
  {
    "name": "take a photograph",
    "trans": [],
    "usphone": "",
    "ukphone": ""
  },
  {
    "name": "take a rest",
    "trans": [],
    "usphone": "",
    "ukphone": ""
  },
  {
    "name": "take off",
    "trans": [],
    "usphone": "",
    "ukphone": ""
  },
  {
    "name": "taste",
    "trans": [],
    "usphone": "",
    "ukphone": ""
  },
  {
    "name": "Thailand",
    "trans": [],
    "usphone": "",
    "ukphone": ""
  },
  {
    "name": "them",
    "trans": [],
    "usphone": "",
    "ukphone": ""
  },
  {
    "name": "these",
    "trans": [],
    "usphone": "",
    "ukphone": ""
  },
  {
    "name": "third",
    "trans": [],
    "usphone": "",
    "ukphone": ""
  },
  {
    "name": "those",
    "trans": [],
    "usphone": "",
    "ukphone": ""
  },
  {
    "name": "tiger",
    "trans": [],
    "usphone": "",
    "ukphone": ""
  },
  {
    "name": "time",
    "trans": [],
    "usphone": "",
    "ukphone": ""
  },
  {
    "name": "together",
    "trans": [],
    "usphone": "",
    "ukphone": ""
  },
  {
    "name": "touch",
    "trans": [],
    "usphone": "",
    "ukphone": ""
  },
  {
    "name": "train",
    "trans": [],
    "usphone": "",
    "ukphone": ""
  },
  {
    "name": "tree",
    "trans": [],
    "usphone": "",
    "ukphone": ""
  },
  {
    "name": "triangle",
    "trans": [],
    "usphone": "",
    "ukphone": ""
  },
  {
    "name": "trousers",
    "trans": [],
    "usphone": "",
    "ukphone": ""
  },
  {
    "name": "turn off",
    "trans": [],
    "usphone": "",
    "ukphone": ""
  },
  {
    "name": "UK",
    "trans": [],
    "usphone": "",
    "ukphone": ""
  },
  {
    "name": "uncle",
    "trans": [],
    "usphone": "",
    "ukphone": ""
  },
  {
    "name": "walk",
    "trans": [],
    "usphone": "",
    "ukphone": ""
  },
  {
    "name": "wall",
    "trans": [],
    "usphone": "",
    "ukphone": ""
  },
  {
    "name": "water",
    "trans": [],
    "usphone": "",
    "ukphone": ""
  },
  {
    "name": "whale",
    "trans": [],
    "usphone": "",
    "ukphone": ""
  },
  {
    "name": "window",
    "trans": [],
    "usphone": "",
    "ukphone": ""
  },
  {
    "name": "winter",
    "trans": [],
    "usphone": "",
    "ukphone": ""
  },
  {
    "name": "with",
    "trans": [],
    "usphone": "",
    "ukphone": ""
  },
  {
    "name": "wolf",
    "trans": [],
    "usphone": "",
    "ukphone": ""
  },
  {
    "name": "word",
    "trans": [],
    "usphone": "",
    "ukphone": ""
  },
  {
    "name": "yourself",
    "trans": [],
    "usphone": "",
    "ukphone": ""
  },
  {
    "name": "yuan",
    "trans": [],
    "usphone": "",
    "ukphone": ""
  },
  {
    "name": "zebra",
    "trans": [],
    "usphone": "",
    "ukphone": ""
  },
  {
    "name": "zoo",
    "trans": [],
    "usphone": "",
    "ukphone": ""
  }
]