[
  {
    "name": "attract",
    "trans": [],
    "usphone": "",
    "ukphone": ""
  },
  {
    "name": "a great number of",
    "trans": [],
    "usphone": "",
    "ukphone": ""
  },
  {
    "name": "fetch",
    "trans": [],
    "usphone": "",
    "ukphone": ""
  },
  {
    "name": "introduce",
    "trans": [],
    "usphone": "",
    "ukphone": ""
  },
  {
    "name": "detail",
    "trans": [],
    "usphone": "",
    "ukphone": ""
  },
  {
    "name": "strange",
    "trans": [],
    "usphone": "",
    "ukphone": ""
  },
  {
    "name": "pine",
    "trans": [],
    "usphone": "",
    "ukphone": ""
  },
  {
    "name": "lie in",
    "trans": [],
    "usphone": "",
    "ukphone": ""
  },
  {
    "name": "length",
    "trans": [],
    "usphone": "",
    "ukphone": ""
  },
  {
    "name": "waterfall",
    "trans": [],
    "usphone": "",
    "ukphone": ""
  },
  {
    "name": "height",
    "trans": [],
    "usphone": "",
    "ukphone": ""
  },
  {
    "name": "grand",
    "trans": [],
    "usphone": "",
    "ukphone": ""
  },
  {
    "name": "imperial",
    "trans": [],
    "usphone": "",
    "ukphone": ""
  },
  {
    "name": "carve",
    "trans": [],
    "usphone": "",
    "ukphone": ""
  },
  {
    "name": "stone",
    "trans": [],
    "usphone": "",
    "ukphone": ""
  },
  {
    "name": "guard",
    "trans": [],
    "usphone": "",
    "ukphone": ""
  },
  {
    "name": "heaven",
    "trans": [],
    "usphone": "",
    "ukphone": ""
  },
  {
    "name": "comment",
    "trans": [],
    "usphone": "",
    "ukphone": ""
  },
  {
    "name": "responsibility",
    "trans": [],
    "usphone": "",
    "ukphone": ""
  },
  {
    "name": "gradually",
    "trans": [],
    "usphone": "",
    "ukphone": ""
  },
  {
    "name": "marble",
    "trans": [],
    "usphone": "",
    "ukphone": ""
  },
  {
    "name": "entire",
    "trans": [],
    "usphone": "",
    "ukphone": ""
  },
  {
    "name": "branch",
    "trans": [],
    "usphone": "",
    "ukphone": ""
  },
  {
    "name": "construction",
    "trans": [],
    "usphone": "",
    "ukphone": ""
  },
  {
    "name": "state",
    "trans": [],
    "usphone": "",
    "ukphone": ""
  },
  {
    "name": "remain",
    "trans": [],
    "usphone": "",
    "ukphone": ""
  },
  {
    "name": "brick",
    "trans": [],
    "usphone": "",
    "ukphone": ""
  },
  {
    "name": "separate",
    "trans": [],
    "usphone": "",
    "ukphone": ""
  },
  {
    "name": "enemy",
    "trans": [],
    "usphone": "",
    "ukphone": ""
  },
  {
    "name": "expect",
    "trans": [],
    "usphone": "",
    "ukphone": ""
  },
  {
    "name": "treasure",
    "trans": [],
    "usphone": "",
    "ukphone": ""
  },
  {
    "name": "civilization",
    "trans": [],
    "usphone": "",
    "ukphone": ""
  },
  {
    "name": "suppose",
    "trans": [],
    "usphone": "",
    "ukphone": ""
  },
  {
    "name": "attraction",
    "trans": [],
    "usphone": "",
    "ukphone": ""
  },
  {
    "name": "major",
    "trans": [],
    "usphone": "",
    "ukphone": ""
  },
  {
    "name": "cocoa",
    "trans": [],
    "usphone": "",
    "ukphone": ""
  },
  {
    "name": "porcelain",
    "trans": [],
    "usphone": "",
    "ukphone": ""
  },
  {
    "name": "export",
    "trans": [],
    "usphone": "",
    "ukphone": ""
  },
  {
    "name": "mild",
    "trans": [],
    "usphone": "",
    "ukphone": ""
  },
  {
    "name": "unique",
    "trans": [],
    "usphone": "",
    "ukphone": ""
  },
  {
    "name": "topic",
    "trans": [],
    "usphone": "",
    "ukphone": ""
  },
  {
    "name": "world-famous",
    "trans": [],
    "usphone": "",
    "ukphone": ""
  },
  {
    "name": "firewood",
    "trans": [],
    "usphone": "",
    "ukphone": ""
  },
  {
    "name": "sauce",
    "trans": [],
    "usphone": "",
    "ukphone": ""
  },
  {
    "name": "vinegar",
    "trans": [],
    "usphone": "",
    "ukphone": ""
  },
  {
    "name": "pioneer",
    "trans": [],
    "usphone": "",
    "ukphone": ""
  },
  {
    "name": "B.C.",
    "trans": [],
    "usphone": "",
    "ukphone": ""
  },
  {
    "name": "thinker",
    "trans": [],
    "usphone": "",
    "ukphone": ""
  },
  {
    "name": "wise",
    "trans": [],
    "usphone": "",
    "ukphone": ""
  },
  {
    "name": "kindness",
    "trans": [],
    "usphone": "",
    "ukphone": ""
  },
  {
    "name": "philosopher",
    "trans": [],
    "usphone": "",
    "ukphone": ""
  },
  {
    "name": "influence",
    "trans": [],
    "usphone": "",
    "ukphone": ""
  },
  {
    "name": "whom",
    "trans": [],
    "usphone": "",
    "ukphone": ""
  },
  {
    "name": "pass away",
    "trans": [],
    "usphone": "",
    "ukphone": ""
  },
  {
    "name": "unite",
    "trans": [],
    "usphone": "",
    "ukphone": ""
  },
  {
    "name": "defeat",
    "trans": [],
    "usphone": "",
    "ukphone": ""
  },
  {
    "name": "set up",
    "trans": [],
    "usphone": "",
    "ukphone": ""
  },
  {
    "name": "empire",
    "trans": [],
    "usphone": "",
    "ukphone": ""
  },
  {
    "name": "forever",
    "trans": [],
    "usphone": "",
    "ukphone": ""
  },
  {
    "name": "come to an end",
    "trans": [],
    "usphone": "",
    "ukphone": ""
  },
  {
    "name": "captain",
    "trans": [],
    "usphone": "",
    "ukphone": ""
  },
  {
    "name": "lead",
    "trans": [],
    "usphone": "",
    "ukphone": ""
  },
  {
    "name": "compass",
    "trans": [],
    "usphone": "",
    "ukphone": ""
  },
  {
    "name": "sailing",
    "trans": [],
    "usphone": "",
    "ukphone": ""
  },
  {
    "name": "sail",
    "trans": [],
    "usphone": "",
    "ukphone": ""
  },
  {
    "name": "coast",
    "trans": [],
    "usphone": "",
    "ukphone": ""
  },
  {
    "name": "unfortunately",
    "trans": [],
    "usphone": "",
    "ukphone": ""
  },
  {
    "name": "birth",
    "trans": [],
    "usphone": "",
    "ukphone": ""
  },
  {
    "name": "trade",
    "trans": [],
    "usphone": "",
    "ukphone": ""
  },
  {
    "name": "missile",
    "trans": [],
    "usphone": "",
    "ukphone": ""
  },
  {
    "name": "graduation",
    "trans": [],
    "usphone": "",
    "ukphone": ""
  },
  {
    "name": "university",
    "trans": [],
    "usphone": "",
    "ukphone": ""
  },
  {
    "name": "Pacific",
    "trans": [],
    "usphone": "",
    "ukphone": ""
  },
  {
    "name": "further",
    "trans": [],
    "usphone": "",
    "ukphone": ""
  },
  {
    "name": "degree",
    "trans": [],
    "usphone": "",
    "ukphone": ""
  },
  {
    "name": "aerospace",
    "trans": [],
    "usphone": "",
    "ukphone": ""
  },
  {
    "name": "graduate",
    "trans": [],
    "usphone": "",
    "ukphone": ""
  },
  {
    "name": "researcher",
    "trans": [],
    "usphone": "",
    "ukphone": ""
  },
  {
    "name": "theory",
    "trans": [],
    "usphone": "",
    "ukphone": ""
  },
  {
    "name": "motherland",
    "trans": [],
    "usphone": "",
    "ukphone": ""
  },
  {
    "name": "blank",
    "trans": [],
    "usphone": "",
    "ukphone": ""
  },
  {
    "name": "institute",
    "trans": [],
    "usphone": "",
    "ukphone": ""
  },
  {
    "name": "charge",
    "trans": [],
    "usphone": "",
    "ukphone": ""
  },
  {
    "name": "in charge of",
    "trans": [],
    "usphone": "",
    "ukphone": ""
  },
  {
    "name": "spacecraft",
    "trans": [],
    "usphone": "",
    "ukphone": ""
  },
  {
    "name": "related",
    "trans": [],
    "usphone": "",
    "ukphone": ""
  },
  {
    "name": "youth",
    "trans": [],
    "usphone": "",
    "ukphone": ""
  },
  {
    "name": "devotion",
    "trans": [],
    "usphone": "",
    "ukphone": ""
  },
  {
    "name": "express",
    "trans": [],
    "usphone": "",
    "ukphone": ""
  },
  {
    "name": "career",
    "trans": [],
    "usphone": "",
    "ukphone": ""
  },
  {
    "name": "destination",
    "trans": [],
    "usphone": "",
    "ukphone": ""
  },
  {
    "name": "hybrid",
    "trans": [],
    "usphone": "",
    "ukphone": ""
  },
  {
    "name": "gunpowder",
    "trans": [],
    "usphone": "",
    "ukphone": ""
  },
  {
    "name": "sailor",
    "trans": [],
    "usphone": "",
    "ukphone": ""
  },
  {
    "name": "discovery",
    "trans": [],
    "usphone": "",
    "ukphone": ""
  },
  {
    "name": "firework",
    "trans": [],
    "usphone": "",
    "ukphone": ""
  },
  {
    "name": "Arab",
    "trans": [],
    "usphone": "",
    "ukphone": ""
  },
  {
    "name": "eastern",
    "trans": [],
    "usphone": "",
    "ukphone": ""
  },
  {
    "name": "bark",
    "trans": [],
    "usphone": "",
    "ukphone": ""
  },
  {
    "name": "rag",
    "trans": [],
    "usphone": "",
    "ukphone": ""
  },
  {
    "name": "clay",
    "trans": [],
    "usphone": "",
    "ukphone": ""
  },
  {
    "name": "ink",
    "trans": [],
    "usphone": "",
    "ukphone": ""
  },
  {
    "name": "express",
    "trans": [],
    "usphone": "",
    "ukphone": ""
  },
  {
    "name": "career",
    "trans": [],
    "usphone": "",
    "ukphone": ""
  },
  {
    "name": "destination",
    "trans": [],
    "usphone": "",
    "ukphone": ""
  },
  {
    "name": "hybrid",
    "trans": [],
    "usphone": "",
    "ukphone": ""
  },
  {
    "name": "gunpowder",
    "trans": [],
    "usphone": "",
    "ukphone": ""
  },
  {
    "name": "sailor",
    "trans": [],
    "usphone": "",
    "ukphone": ""
  },
  {
    "name": "discovery",
    "trans": [],
    "usphone": "",
    "ukphone": ""
  },
  {
    "name": "firework",
    "trans": [],
    "usphone": "",
    "ukphone": ""
  },
  {
    "name": "Arab",
    "trans": [],
    "usphone": "",
    "ukphone": ""
  },
  {
    "name": "eastern",
    "trans": [],
    "usphone": "",
    "ukphone": ""
  },
  {
    "name": "bark",
    "trans": [],
    "usphone": "",
    "ukphone": ""
  },
  {
    "name": "rag",
    "trans": [],
    "usphone": "",
    "ukphone": ""
  },
  {
    "name": "clay",
    "trans": [],
    "usphone": "",
    "ukphone": ""
  },
  {
    "name": "ink",
    "trans": [],
    "usphone": "",
    "ukphone": ""
  },
  {
    "name": "telegraph",
    "trans": [],
    "usphone": "",
    "ukphone": ""
  },
  {
    "name": "photographic",
    "trans": [],
    "usphone": "",
    "ukphone": ""
  },
  {
    "name": "duty",
    "trans": [],
    "usphone": "",
    "ukphone": ""
  },
  {
    "name": "neither",
    "trans": [],
    "usphone": "",
    "ukphone": ""
  },
  {
    "name": "nor",
    "trans": [],
    "usphone": "",
    "ukphone": ""
  },
  {
    "name": "neither nor",
    "trans": [],
    "usphone": "",
    "ukphone": ""
  },
  {
    "name": "remarry",
    "trans": [],
    "usphone": "",
    "ukphone": ""
  },
  {
    "name": "stepmother",
    "trans": [],
    "usphone": "",
    "ukphone": ""
  },
  {
    "name": "license",
    "trans": [],
    "usphone": "",
    "ukphone": ""
  },
  {
    "name": "lawyer",
    "trans": [],
    "usphone": "",
    "ukphone": ""
  },
  {
    "name": "trust",
    "trans": [],
    "usphone": "",
    "ukphone": ""
  },
  {
    "name": "highly",
    "trans": [],
    "usphone": "",
    "ukphone": ""
  },
  {
    "name": "politician",
    "trans": [],
    "usphone": "",
    "ukphone": ""
  },
  {
    "name": "elect",
    "trans": [],
    "usphone": "",
    "ukphone": ""
  },
  {
    "name": "Civil War",
    "trans": [],
    "usphone": "",
    "ukphone": ""
  },
  {
    "name": "break out",
    "trans": [],
    "usphone": "",
    "ukphone": ""
  },
  {
    "name": "union",
    "trans": [],
    "usphone": "",
    "ukphone": ""
  },
  {
    "name": "slave",
    "trans": [],
    "usphone": "",
    "ukphone": ""
  },
  {
    "name": "get rid of",
    "trans": [],
    "usphone": "",
    "ukphone": ""
  },
  {
    "name": "set free",
    "trans": [],
    "usphone": "",
    "ukphone": ""
  },
  {
    "name": "shoot",
    "trans": [],
    "usphone": "",
    "ukphone": ""
  },
  {
    "name": "break up",
    "trans": [],
    "usphone": "",
    "ukphone": ""
  },
  {
    "name": "unit",
    "trans": [],
    "usphone": "",
    "ukphone": ""
  },
  {
    "name": "walker",
    "trans": [],
    "usphone": "",
    "ukphone": ""
  },
  {
    "name": "backwards",
    "trans": [],
    "usphone": "",
    "ukphone": ""
  },
  {
    "name": "concern",
    "trans": [],
    "usphone": "",
    "ukphone": ""
  },
  {
    "name": "content",
    "trans": [],
    "usphone": "",
    "ukphone": ""
  },
  {
    "name": "failure",
    "trans": [],
    "usphone": "",
    "ukphone": ""
  },
  {
    "name": "brief",
    "trans": [],
    "usphone": "",
    "ukphone": ""
  },
  {
    "name": "achievement",
    "trans": [],
    "usphone": "",
    "ukphone": ""
  },
  {
    "name": "Egyptian",
    "trans": [],
    "usphone": "",
    "ukphone": ""
  },
  {
    "name": "pyramid",
    "trans": [],
    "usphone": "",
    "ukphone": ""
  },
  {
    "name": "tomb",
    "trans": [],
    "usphone": "",
    "ukphone": ""
  },
  {
    "name": "complete",
    "trans": [],
    "usphone": "",
    "ukphone": ""
  },
  {
    "name": "A.D.",
    "trans": [],
    "usphone": "",
    "ukphone": ""
  },
  {
    "name": "scientific",
    "trans": [],
    "usphone": "",
    "ukphone": ""
  },
  {
    "name": "ton",
    "trans": [],
    "usphone": "",
    "ukphone": ""
  },
  {
    "name": "fix",
    "trans": [],
    "usphone": "",
    "ukphone": ""
  },
  {
    "name": "tool",
    "trans": [],
    "usphone": "",
    "ukphone": ""
  },
  {
    "name": "mystery",
    "trans": [],
    "usphone": "",
    "ukphone": ""
  },
  {
    "name": "completion",
    "trans": [],
    "usphone": "",
    "ukphone": ""
  },
  {
    "name": "graze",
    "trans": [],
    "usphone": "",
    "ukphone": ""
  },
  {
    "name": "make fun of",
    "trans": [],
    "usphone": "",
    "ukphone": ""
  },
  {
    "name": "wolf",
    "trans": [],
    "usphone": "",
    "ukphone": ""
  },
  {
    "name": "iron",
    "trans": [],
    "usphone": "",
    "ukphone": ""
  },
  {
    "name": "glory",
    "trans": [],
    "usphone": "",
    "ukphone": ""
  },
  {
    "name": "peasant",
    "trans": [],
    "usphone": "",
    "ukphone": ""
  },
  {
    "name": "battle",
    "trans": [],
    "usphone": "",
    "ukphone": ""
  },
  {
    "name": "battlefield",
    "trans": [],
    "usphone": "",
    "ukphone": ""
  },
  {
    "name": "memory",
    "trans": [],
    "usphone": "",
    "ukphone": ""
  },
  {
    "name": "in memory of",
    "trans": [],
    "usphone": "",
    "ukphone": ""
  },
  {
    "name": "romantic",
    "trans": [],
    "usphone": "",
    "ukphone": ""
  },
  {
    "name": "tale",
    "trans": [],
    "usphone": "",
    "ukphone": ""
  },
  {
    "name": "home and abroad",
    "trans": [],
    "usphone": "",
    "ukphone": ""
  },
  {
    "name": "scenery",
    "trans": [],
    "usphone": "",
    "ukphone": ""
  },
  {
    "name": "graze",
    "trans": [],
    "usphone": "",
    "ukphone": ""
  },
  {
    "name": "make fun of",
    "trans": [],
    "usphone": "",
    "ukphone": ""
  },
  {
    "name": "wolf",
    "trans": [],
    "usphone": "",
    "ukphone": ""
  },
  {
    "name": "iron",
    "trans": [],
    "usphone": "",
    "ukphone": ""
  },
  {
    "name": "glory",
    "trans": [],
    "usphone": "",
    "ukphone": ""
  },
  {
    "name": "peasant",
    "trans": [],
    "usphone": "",
    "ukphone": ""
  },
  {
    "name": "battle",
    "trans": [],
    "usphone": "",
    "ukphone": ""
  },
  {
    "name": "battlefield",
    "trans": [],
    "usphone": "",
    "ukphone": ""
  },
  {
    "name": "memory",
    "trans": [],
    "usphone": "",
    "ukphone": ""
  },
  {
    "name": "in memory of",
    "trans": [],
    "usphone": "",
    "ukphone": ""
  },
  {
    "name": "romantic",
    "trans": [],
    "usphone": "",
    "ukphone": ""
  },
  {
    "name": "tale",
    "trans": [],
    "usphone": "",
    "ukphone": ""
  },
  {
    "name": "home and abroad",
    "trans": [],
    "usphone": "",
    "ukphone": ""
  },
  {
    "name": "scenery",
    "trans": [],
    "usphone": "",
    "ukphone": ""
  },
  {
    "name": "would rather than",
    "trans": [],
    "usphone": "",
    "ukphone": ""
  },
  {
    "name": "actress",
    "trans": [],
    "usphone": "",
    "ukphone": ""
  },
  {
    "name": "charming",
    "trans": [],
    "usphone": "",
    "ukphone": ""
  },
  {
    "name": "educational",
    "trans": [],
    "usphone": "",
    "ukphone": ""
  },
  {
    "name": "science fiction",
    "trans": [],
    "usphone": "",
    "ukphone": ""
  },
  {
    "name": "tragedy",
    "trans": [],
    "usphone": "",
    "ukphone": ""
  },
  {
    "name": "documentary",
    "trans": [],
    "usphone": "",
    "ukphone": ""
  },
  {
    "name": "comedy",
    "trans": [],
    "usphone": "",
    "ukphone": ""
  },
  {
    "name": "ending",
    "trans": [],
    "usphone": "",
    "ukphone": ""
  },
  {
    "name": "drawing",
    "trans": [],
    "usphone": "",
    "ukphone": ""
  },
  {
    "name": "mission",
    "trans": [],
    "usphone": "",
    "ukphone": ""
  },
  {
    "name": "adventure",
    "trans": [],
    "usphone": "",
    "ukphone": ""
  },
  {
    "name": "mysterious",
    "trans": [],
    "usphone": "",
    "ukphone": ""
  },
  {
    "name": "crew",
    "trans": [],
    "usphone": "",
    "ukphone": ""
  },
  {
    "name": "rescue",
    "trans": [],
    "usphone": "",
    "ukphone": ""
  },
  {
    "name": "award",
    "trans": [],
    "usphone": "",
    "ukphone": ""
  },
  {
    "name": "literature",
    "trans": [],
    "usphone": "",
    "ukphone": ""
  },
  {
    "name": "classic",
    "trans": [],
    "usphone": "",
    "ukphone": ""
  },
  {
    "name": "in one's view",
    "trans": [],
    "usphone": "",
    "ukphone": ""
  },
  {
    "name": "overcome",
    "trans": [],
    "usphone": "",
    "ukphone": ""
  },
  {
    "name": "statement",
    "trans": [],
    "usphone": "",
    "ukphone": ""
  },
  {
    "name": "literary",
    "trans": [],
    "usphone": "",
    "ukphone": ""
  },
  {
    "name": "society",
    "trans": [],
    "usphone": "",
    "ukphone": ""
  },
  {
    "name": "moving",
    "trans": [],
    "usphone": "",
    "ukphone": ""
  },
  {
    "name": "poetry",
    "trans": [],
    "usphone": "",
    "ukphone": ""
  },
  {
    "name": "poet",
    "trans": [],
    "usphone": "",
    "ukphone": ""
  },
  {
    "name": "playwright",
    "trans": [],
    "usphone": "",
    "ukphone": ""
  },
  {
    "name": "drama",
    "trans": [],
    "usphone": "",
    "ukphone": ""
  },
  {
    "name": "scene",
    "trans": [],
    "usphone": "",
    "ukphone": ""
  },
  {
    "name": "kiss",
    "trans": [],
    "usphone": "",
    "ukphone": ""
  },
  {
    "name": "masterpiece",
    "trans": [],
    "usphone": "",
    "ukphone": ""
  },
  {
    "name": "district",
    "trans": [],
    "usphone": "",
    "ukphone": ""
  },
  {
    "name": "unlike",
    "trans": [],
    "usphone": "",
    "ukphone": ""
  },
  {
    "name": "rainbow",
    "trans": [],
    "usphone": "",
    "ukphone": ""
  },
  {
    "name": "inspiration",
    "trans": [],
    "usphone": "",
    "ukphone": ""
  },
  {
    "name": "eventually",
    "trans": [],
    "usphone": "",
    "ukphone": ""
  },
  {
    "name": "golden",
    "trans": [],
    "usphone": "",
    "ukphone": ""
  },
  {
    "name": "monk",
    "trans": [],
    "usphone": "",
    "ukphone": ""
  },
  {
    "name": "narrator",
    "trans": [],
    "usphone": "",
    "ukphone": ""
  },
  {
    "name": "husband",
    "trans": [],
    "usphone": "",
    "ukphone": ""
  },
  {
    "name": "precious",
    "trans": [],
    "usphone": "",
    "ukphone": ""
  },
  {
    "name": "possession",
    "trans": [],
    "usphone": "",
    "ukphone": ""
  },
  {
    "name": "wealth",
    "trans": [],
    "usphone": "",
    "ukphone": ""
  },
  {
    "name": "chain",
    "trans": [],
    "usphone": "",
    "ukphone": ""
  },
  {
    "name": "sudden",
    "trans": [],
    "usphone": "",
    "ukphone": ""
  },
  {
    "name": "all of a sudden",
    "trans": [],
    "usphone": "",
    "ukphone": ""
  },
  {
    "name": "cut off",
    "trans": [],
    "usphone": "",
    "ukphone": ""
  },
  {
    "name": "live through",
    "trans": [],
    "usphone": "",
    "ukphone": ""
  },
  {
    "name": "possibly",
    "trans": [],
    "usphone": "",
    "ukphone": ""
  },
  {
    "name": "comb",
    "trans": [],
    "usphone": "",
    "ukphone": ""
  },
  {
    "name": "jeweled",
    "trans": [],
    "usphone": "",
    "ukphone": ""
  },
  {
    "name": "rim",
    "trans": [],
    "usphone": "",
    "ukphone": ""
  },
  {
    "name": "long for",
    "trans": [],
    "usphone": "",
    "ukphone": ""
  },
  {
    "name": "hunt",
    "trans": [],
    "usphone": "",
    "ukphone": ""
  },
  {
    "name": "at present",
    "trans": [],
    "usphone": "",
    "ukphone": ""
  },
  {
    "name": "couple",
    "trans": [],
    "usphone": "",
    "ukphone": ""
  },
  {
    "name": "the couple",
    "trans": [],
    "usphone": "",
    "ukphone": ""
  },
  {
    "name": "first of all",
    "trans": [],
    "usphone": "",
    "ukphone": ""
  },
  {
    "name": "exchange",
    "trans": [],
    "usphone": "",
    "ukphone": ""
  },
  {
    "name": "chalk",
    "trans": [],
    "usphone": "",
    "ukphone": ""
  },
  {
    "name": "dozen",
    "trans": [],
    "usphone": "",
    "ukphone": ""
  },
  {
    "name": "dozens of",
    "trans": [],
    "usphone": "",
    "ukphone": ""
  },
  {
    "name": "excellence",
    "trans": [],
    "usphone": "",
    "ukphone": ""
  },
  {
    "name": "valuable",
    "trans": [],
    "usphone": "",
    "ukphone": ""
  },
  {
    "name": "bottom",
    "trans": [],
    "usphone": "",
    "ukphone": ""
  },
  {
    "name": "unforgettable",
    "trans": [],
    "usphone": "",
    "ukphone": ""
  },
  {
    "name": "joy",
    "trans": [],
    "usphone": "",
    "ukphone": ""
  },
  {
    "name": "royal",
    "trans": [],
    "usphone": "",
    "ukphone": ""
  },
  {
    "name": "recall",
    "trans": [],
    "usphone": "",
    "ukphone": ""
  },
  {
    "name": "competition",
    "trans": [],
    "usphone": "",
    "ukphone": ""
  },
  {
    "name": "custom",
    "trans": [],
    "usphone": "",
    "ukphone": ""
  },
  {
    "name": "principal",
    "trans": [],
    "usphone": "",
    "ukphone": ""
  },
  {
    "name": "diploma",
    "trans": [],
    "usphone": "",
    "ukphone": ""
  },
  {
    "name": "congratulate",
    "trans": [],
    "usphone": "",
    "ukphone": ""
  },
  {
    "name": "possibility",
    "trans": [],
    "usphone": "",
    "ukphone": ""
  },
  {
    "name": "thankful",
    "trans": [],
    "usphone": "",
    "ukphone": ""
  },
  {
    "name": "in a hurry",
    "trans": [],
    "usphone": "",
    "ukphone": ""
  },
  {
    "name": "hug",
    "trans": [],
    "usphone": "",
    "ukphone": ""
  },
  {
    "name": "in time",
    "trans": [],
    "usphone": "",
    "ukphone": ""
  },
  {
    "name": "promise",
    "trans": [],
    "usphone": "",
    "ukphone": ""
  },
  {
    "name": "conclude",
    "trans": [],
    "usphone": "",
    "ukphone": ""
  },
  {
    "name": "pound",
    "trans": [],
    "usphone": "",
    "ukphone": ""
  },
  {
    "name": "absent",
    "trans": [],
    "usphone": "",
    "ukphone": ""
  },
  {
    "name": "alive",
    "trans": [],
    "usphone": "",
    "ukphone": ""
  },
  {
    "name": "sharply",
    "trans": [],
    "usphone": "",
    "ukphone": ""
  },
  {
    "name": "asleep",
    "trans": [],
    "usphone": "",
    "ukphone": ""
  },
  {
    "name": "awake",
    "trans": [],
    "usphone": "",
    "ukphone": ""
  },
  {
    "name": "ant",
    "trans": [],
    "usphone": "",
    "ukphone": ""
  },
  {
    "name": "hard-working",
    "trans": [],
    "usphone": "",
    "ukphone": ""
  },
  {
    "name": "unless",
    "trans": [],
    "usphone": "",
    "ukphone": ""
  },
  {
    "name": "truth",
    "trans": [],
    "usphone": "",
    "ukphone": ""
  },
  {
    "name": "operate",
    "trans": [],
    "usphone": "",
    "ukphone": ""
  },
  {
    "name": "instruction",
    "trans": [],
    "usphone": "",
    "ukphone": ""
  },
  {
    "name": "northwestern",
    "trans": [],
    "usphone": "",
    "ukphone": ""
  },
  {
    "name": "flow",
    "trans": [],
    "usphone": "",
    "ukphone": ""
  },
  {
    "name": "appearance",
    "trans": [],
    "usphone": "",
    "ukphone": ""
  },
  {
    "name": "muddy",
    "trans": [],
    "usphone": "",
    "ukphone": ""
  },
  {
    "name": "idiom",
    "trans": [],
    "usphone": "",
    "ukphone": ""
  },
  {
    "name": "argument",
    "trans": [],
    "usphone": "",
    "ukphone": ""
  },
  {
    "name": "slap",
    "trans": [],
    "usphone": "",
    "ukphone": ""
  },
  {
    "name": "till",
    "trans": [],
    "usphone": "",
    "ukphone": ""
  },
  {
    "name": "mud",
    "trans": [],
    "usphone": "",
    "ukphone": ""
  },
  {
    "name": "sink",
    "trans": [],
    "usphone": "",
    "ukphone": ""
  },
  {
    "name": "reply",
    "trans": [],
    "usphone": "",
    "ukphone": ""
  },
  {
    "name": "erase",
    "trans": [],
    "usphone": "",
    "ukphone": ""
  },
  {
    "name": "response",
    "trans": [],
    "usphone": "",
    "ukphone": ""
  }
]