[
  {
    "name": "frequently",
    "trans": [],
    "usphone": "",
    "ukphone": ""
  },
  {
    "name": "recite",
    "trans": [],
    "usphone": "",
    "ukphone": ""
  },
  {
    "name": "trial",
    "trans": [],
    "usphone": "",
    "ukphone": ""
  },
  {
    "name": "educator",
    "trans": [],
    "usphone": "",
    "ukphone": ""
  },
  {
    "name": "Polish",
    "trans": [],
    "usphone": "",
    "ukphone": ""
  },
  {
    "name": "poetry",
    "trans": [],
    "usphone": "",
    "ukphone": ""
  },
  {
    "name": "compose",
    "trans": [],
    "usphone": "",
    "ukphone": ""
  },
  {
    "name": "prose",
    "trans": [],
    "usphone": "",
    "ukphone": ""
  },
  {
    "name": "patriotic",
    "trans": [],
    "usphone": "",
    "ukphone": ""
  },
  {
    "name": "acquire",
    "trans": [],
    "usphone": "",
    "ukphone": ""
  },
  {
    "name": "willingly",
    "trans": [],
    "usphone": "",
    "ukphone": ""
  },
  {
    "name": "poet",
    "trans": [],
    "usphone": "",
    "ukphone": ""
  },
  {
    "name": "aid",
    "trans": [],
    "usphone": "",
    "ukphone": ""
  },
  {
    "name": "experiment",
    "trans": [],
    "usphone": "",
    "ukphone": ""
  },
  {
    "name": "gas",
    "trans": [],
    "usphone": "",
    "ukphone": ""
  },
  {
    "name": "compound",
    "trans": [],
    "usphone": "",
    "ukphone": ""
  },
  {
    "name": "practically",
    "trans": [],
    "usphone": "",
    "ukphone": ""
  },
  {
    "name": "experimental",
    "trans": [],
    "usphone": "",
    "ukphone": ""
  },
  {
    "name": "somehow",
    "trans": [],
    "usphone": "",
    "ukphone": ""
  },
  {
    "name": "nickname",
    "trans": [],
    "usphone": "",
    "ukphone": ""
  },
  {
    "name": "herd-boy",
    "trans": [],
    "usphone": "",
    "ukphone": ""
  },
  {
    "name": "calf",
    "trans": [],
    "usphone": "",
    "ukphone": ""
  },
  {
    "name": "slingshot",
    "trans": [],
    "usphone": "",
    "ukphone": ""
  },
  {
    "name": "gather",
    "trans": [],
    "usphone": "",
    "ukphone": ""
  },
  {
    "name": "honey",
    "trans": [],
    "usphone": "",
    "ukphone": ""
  },
  {
    "name": "stream",
    "trans": [],
    "usphone": "",
    "ukphone": ""
  },
  {
    "name": "twine",
    "trans": [],
    "usphone": "",
    "ukphone": ""
  },
  {
    "name": "wire",
    "trans": [],
    "usphone": "",
    "ukphone": ""
  },
  {
    "name": "unruly",
    "trans": [],
    "usphone": "",
    "ukphone": ""
  },
  {
    "name": "donkey",
    "trans": [],
    "usphone": "",
    "ukphone": ""
  },
  {
    "name": "bush",
    "trans": [],
    "usphone": "",
    "ukphone": ""
  },
  {
    "name": "unseat",
    "trans": [],
    "usphone": "",
    "ukphone": ""
  },
  {
    "name": "embarrass",
    "trans": [],
    "usphone": "",
    "ukphone": ""
  },
  {
    "name": "dignity",
    "trans": [],
    "usphone": "",
    "ukphone": ""
  },
  {
    "name": "suffer",
    "trans": [],
    "usphone": "",
    "ukphone": ""
  },
  {
    "name": "fate",
    "trans": [],
    "usphone": "",
    "ukphone": ""
  },
  {
    "name": "defeat",
    "trans": [],
    "usphone": "",
    "ukphone": ""
  },
  {
    "name": "opponent",
    "trans": [],
    "usphone": "",
    "ukphone": ""
  },
  {
    "name": "dishonour",
    "trans": [],
    "usphone": "",
    "ukphone": ""
  },
  {
    "name": "run away",
    "trans": [],
    "usphone": "",
    "ukphone": ""
  },
  {
    "name": "by heart",
    "trans": [],
    "usphone": "",
    "ukphone": ""
  },
  {
    "name": "take turns",
    "trans": [],
    "usphone": "",
    "ukphone": ""
  },
  {
    "name": "take it in turns",
    "trans": [],
    "usphone": "",
    "ukphone": ""
  },
  {
    "name": "lose face",
    "trans": [],
    "usphone": "",
    "ukphone": ""
  },
  {
    "name": "cease",
    "trans": [],
    "usphone": "",
    "ukphone": ""
  },
  {
    "name": "indigo",
    "trans": [],
    "usphone": "",
    "ukphone": ""
  },
  {
    "name": "plumb line",
    "trans": [],
    "usphone": "",
    "ukphone": ""
  },
  {
    "name": "compass",
    "trans": [],
    "usphone": "",
    "ukphone": ""
  },
  {
    "name": "process",
    "trans": [],
    "usphone": "",
    "ukphone": ""
  },
  {
    "name": "thus",
    "trans": [],
    "usphone": "",
    "ukphone": ""
  },
  {
    "name": "press",
    "trans": [],
    "usphone": "",
    "ukphone": ""
  },
  {
    "name": "metal",
    "trans": [],
    "usphone": "",
    "ukphone": ""
  },
  {
    "name": "grindstone",
    "trans": [],
    "usphone": "",
    "ukphone": ""
  },
  {
    "name": "wisdom",
    "trans": [],
    "usphone": "",
    "ukphone": ""
  },
  {
    "name": "conduct",
    "trans": [],
    "usphone": "",
    "ukphone": ""
  },
  {
    "name": "distance",
    "trans": [],
    "usphone": "",
    "ukphone": ""
  },
  {
    "name": "wave",
    "trans": [],
    "usphone": "",
    "ukphone": ""
  },
  {
    "name": "carriage",
    "trans": [],
    "usphone": "",
    "ukphone": ""
  },
  {
    "name": "pile",
    "trans": [],
    "usphone": "",
    "ukphone": ""
  },
  {
    "name": "dragon",
    "trans": [],
    "usphone": "",
    "ukphone": ""
  },
  {
    "name": "deed",
    "trans": [],
    "usphone": "",
    "ukphone": ""
  },
  {
    "name": "virtue",
    "trans": [],
    "usphone": "",
    "ukphone": ""
  },
  {
    "name": "profound",
    "trans": [],
    "usphone": "",
    "ukphone": ""
  },
  {
    "name": "sage",
    "trans": [],
    "usphone": "",
    "ukphone": ""
  },
  {
    "name": "thoroughbred",
    "trans": [],
    "usphone": "",
    "ukphone": ""
  },
  {
    "name": "pace",
    "trans": [],
    "usphone": "",
    "ukphone": ""
  },
  {
    "name": "leap",
    "trans": [],
    "usphone": "",
    "ukphone": ""
  },
  {
    "name": "nag",
    "trans": [],
    "usphone": "",
    "ukphone": ""
  },
  {
    "name": "achievement",
    "trans": [],
    "usphone": "",
    "ukphone": ""
  },
  {
    "name": "carve",
    "trans": [],
    "usphone": "",
    "ukphone": ""
  },
  {
    "name": "rotten",
    "trans": [],
    "usphone": "",
    "ukphone": ""
  },
  {
    "name": "persist",
    "trans": [],
    "usphone": "",
    "ukphone": ""
  },
  {
    "name": "inlay",
    "trans": [],
    "usphone": "",
    "ukphone": ""
  },
  {
    "name": "on tiptoe",
    "trans": [],
    "usphone": "",
    "ukphone": ""
  },
  {
    "name": "in the distance",
    "trans": [],
    "usphone": "",
    "ukphone": ""
  },
  {
    "name": "into the distance",
    "trans": [],
    "usphone": "",
    "ukphone": ""
  },
  {
    "name": "make use of",
    "trans": [],
    "usphone": "",
    "ukphone": ""
  },
  {
    "name": "come of",
    "trans": [],
    "usphone": "",
    "ukphone": ""
  },
  {
    "name": "come from",
    "trans": [],
    "usphone": "",
    "ukphone": ""
  },
  {
    "name": "consist in",
    "trans": [],
    "usphone": "",
    "ukphone": ""
  },
  {
    "name": "volunteer",
    "trans": [],
    "usphone": "",
    "ukphone": ""
  },
  {
    "name": "cheetah",
    "trans": [],
    "usphone": "",
    "ukphone": ""
  },
  {
    "name": "threat",
    "trans": [],
    "usphone": "",
    "ukphone": ""
  },
  {
    "name": "purchase",
    "trans": [],
    "usphone": "",
    "ukphone": ""
  },
  {
    "name": "collar",
    "trans": [],
    "usphone": "",
    "ukphone": ""
  },
  {
    "name": "lemonade",
    "trans": [],
    "usphone": "",
    "ukphone": ""
  },
  {
    "name": "donate",
    "trans": [],
    "usphone": "",
    "ukphone": ""
  },
  {
    "name": "wildlife",
    "trans": [],
    "usphone": "",
    "ukphone": ""
  },
  {
    "name": "organisation",
    "trans": [],
    "usphone": "",
    "ukphone": ""
  },
  {
    "name": "twin",
    "trans": [],
    "usphone": "",
    "ukphone": ""
  },
  {
    "name": "launch",
    "trans": [],
    "usphone": "",
    "ukphone": ""
  },
  {
    "name": "database",
    "trans": [],
    "usphone": "",
    "ukphone": ""
  },
  {
    "name": "shelter",
    "trans": [],
    "usphone": "",
    "ukphone": ""
  },
  {
    "name": "earn",
    "trans": [],
    "usphone": "",
    "ukphone": ""
  },
  {
    "name": "urban",
    "trans": [],
    "usphone": "",
    "ukphone": ""
  },
  {
    "name": "request",
    "trans": [],
    "usphone": "",
    "ukphone": ""
  },
  {
    "name": "plastic",
    "trans": [],
    "usphone": "",
    "ukphone": ""
  },
  {
    "name": "march",
    "trans": [],
    "usphone": "",
    "ukphone": ""
  },
  {
    "name": "county",
    "trans": [],
    "usphone": "",
    "ukphone": ""
  },
  {
    "name": "campaign",
    "trans": [],
    "usphone": "",
    "ukphone": ""
  },
  {
    "name": "promote",
    "trans": [],
    "usphone": "",
    "ukphone": ""
  },
  {
    "name": "reusable",
    "trans": [],
    "usphone": "",
    "ukphone": ""
  },
  {
    "name": "urge",
    "trans": [],
    "usphone": "",
    "ukphone": ""
  },
  {
    "name": "movement",
    "trans": [],
    "usphone": "",
    "ukphone": ""
  },
  {
    "name": "gallery",
    "trans": [],
    "usphone": "",
    "ukphone": ""
  },
  {
    "name": "emperor",
    "trans": [],
    "usphone": "",
    "ukphone": ""
  },
  {
    "name": "brick",
    "trans": [],
    "usphone": "",
    "ukphone": ""
  },
  {
    "name": "latest",
    "trans": [],
    "usphone": "",
    "ukphone": ""
  },
  {
    "name": "make a difference",
    "trans": [],
    "usphone": "",
    "ukphone": ""
  },
  {
    "name": "base on",
    "trans": [],
    "usphone": "",
    "ukphone": ""
  },
  {
    "name": "base upon",
    "trans": [],
    "usphone": "",
    "ukphone": ""
  },
  {
    "name": "hang around",
    "trans": [],
    "usphone": "",
    "ukphone": ""
  },
  {
    "name": "Orange County",
    "trans": [],
    "usphone": "",
    "ukphone": ""
  },
  {
    "name": "the Palace Museum",
    "trans": [],
    "usphone": "",
    "ukphone": ""
  },
  {
    "name": "the Forbidden City",
    "trans": [],
    "usphone": "",
    "ukphone": ""
  },
  {
    "name": "boarding school",
    "trans": [],
    "usphone": "",
    "ukphone": ""
  },
  {
    "name": "orphanage",
    "trans": [],
    "usphone": "",
    "ukphone": ""
  },
  {
    "name": "pickup",
    "trans": [],
    "usphone": "",
    "ukphone": ""
  },
  {
    "name": "soccer",
    "trans": [],
    "usphone": "",
    "ukphone": ""
  },
  {
    "name": "mission",
    "trans": [],
    "usphone": "",
    "ukphone": ""
  },
  {
    "name": "educated",
    "trans": [],
    "usphone": "",
    "ukphone": ""
  },
  {
    "name": "deliver",
    "trans": [],
    "usphone": "",
    "ukphone": ""
  },
  {
    "name": "construction",
    "trans": [],
    "usphone": "",
    "ukphone": ""
  },
  {
    "name": "undo",
    "trans": [],
    "usphone": "",
    "ukphone": ""
  },
  {
    "name": "structure",
    "trans": [],
    "usphone": "",
    "ukphone": ""
  },
  {
    "name": "hire",
    "trans": [],
    "usphone": "",
    "ukphone": ""
  },
  {
    "name": "awkward",
    "trans": [],
    "usphone": "",
    "ukphone": ""
  },
  {
    "name": "failure",
    "trans": [],
    "usphone": "",
    "ukphone": ""
  },
  {
    "name": "styling",
    "trans": [],
    "usphone": "",
    "ukphone": ""
  },
  {
    "name": "band",
    "trans": [],
    "usphone": "",
    "ukphone": ""
  },
  {
    "name": "logical",
    "trans": [],
    "usphone": "",
    "ukphone": ""
  },
  {
    "name": "fashionable",
    "trans": [],
    "usphone": "",
    "ukphone": ""
  },
  {
    "name": "crisp",
    "trans": [],
    "usphone": "",
    "ukphone": ""
  },
  {
    "name": "Tanzanian",
    "trans": [],
    "usphone": "",
    "ukphone": ""
  },
  {
    "name": "uniform",
    "trans": [],
    "usphone": "",
    "ukphone": ""
  },
  {
    "name": "regular",
    "trans": [],
    "usphone": "",
    "ukphone": ""
  },
  {
    "name": "crop",
    "trans": [],
    "usphone": "",
    "ukphone": ""
  },
  {
    "name": "regulate",
    "trans": [],
    "usphone": "",
    "ukphone": ""
  },
  {
    "name": "official",
    "trans": [],
    "usphone": "",
    "ukphone": ""
  },
  {
    "name": "haircut",
    "trans": [],
    "usphone": "",
    "ukphone": ""
  },
  {
    "name": "productivity",
    "trans": [],
    "usphone": "",
    "ukphone": ""
  },
  {
    "name": "resource",
    "trans": [],
    "usphone": "",
    "ukphone": ""
  },
  {
    "name": "criticize",
    "trans": [],
    "usphone": "",
    "ukphone": ""
  },
  {
    "name": "intention",
    "trans": [],
    "usphone": "",
    "ukphone": ""
  },
  {
    "name": "assume",
    "trans": [],
    "usphone": "",
    "ukphone": ""
  },
  {
    "name": "consist of",
    "trans": [],
    "usphone": "",
    "ukphone": ""
  },
  {
    "name": "lead up to",
    "trans": [],
    "usphone": "",
    "ukphone": ""
  },
  {
    "name": "off the track",
    "trans": [],
    "usphone": "",
    "ukphone": ""
  },
  {
    "name": "Tanzania",
    "trans": [],
    "usphone": "",
    "ukphone": ""
  },
  {
    "name": "endurance",
    "trans": [],
    "usphone": "",
    "ukphone": ""
  },
  {
    "name": "advertisement",
    "trans": [],
    "usphone": "",
    "ukphone": ""
  },
  {
    "name": "hazardous",
    "trans": [],
    "usphone": "",
    "ukphone": ""
  },
  {
    "name": "wage",
    "trans": [],
    "usphone": "",
    "ukphone": ""
  },
  {
    "name": "explorer",
    "trans": [],
    "usphone": "",
    "ukphone": ""
  },
  {
    "name": "via",
    "trans": [],
    "usphone": "",
    "ukphone": ""
  },
  {
    "name": "pole",
    "trans": [],
    "usphone": "",
    "ukphone": ""
  },
  {
    "name": "expedition",
    "trans": [],
    "usphone": "",
    "ukphone": ""
  },
  {
    "name": "exceptionally",
    "trans": [],
    "usphone": "",
    "ukphone": ""
  },
  {
    "name": "stuck",
    "trans": [],
    "usphone": "",
    "ukphone": ""
  },
  {
    "name": "freezing",
    "trans": [],
    "usphone": "",
    "ukphone": ""
  },
  {
    "name": "disaster",
    "trans": [],
    "usphone": "",
    "ukphone": ""
  },
  {
    "name": "melt",
    "trans": [],
    "usphone": "",
    "ukphone": ""
  },
  {
    "name": "crew",
    "trans": [],
    "usphone": "",
    "ukphone": ""
  },
  {
    "name": "abandon",
    "trans": [],
    "usphone": "",
    "ukphone": ""
  },
  {
    "name": "sink",
    "trans": [],
    "usphone": "",
    "ukphone": ""
  },
  {
    "name": "survive",
    "trans": [],
    "usphone": "",
    "ukphone": ""
  },
  {
    "name": "float",
    "trans": [],
    "usphone": "",
    "ukphone": ""
  },
  {
    "name": "lifeboat",
    "trans": [],
    "usphone": "",
    "ukphone": ""
  },
  {
    "name": "exhausted",
    "trans": [],
    "usphone": "",
    "ukphone": ""
  },
  {
    "name": "rescue",
    "trans": [],
    "usphone": "",
    "ukphone": ""
  },
  {
    "name": "Norwegian",
    "trans": [],
    "usphone": "",
    "ukphone": ""
  },
  {
    "name": "whaling",
    "trans": [],
    "usphone": "",
    "ukphone": ""
  },
  {
    "name": "exhausting",
    "trans": [],
    "usphone": "",
    "ukphone": ""
  },
  {
    "name": "march",
    "trans": [],
    "usphone": "",
    "ukphone": ""
  },
  {
    "name": "continuously",
    "trans": [],
    "usphone": "",
    "ukphone": ""
  },
  {
    "name": "tent",
    "trans": [],
    "usphone": "",
    "ukphone": ""
  },
  {
    "name": "starve",
    "trans": [],
    "usphone": "",
    "ukphone": ""
  },
  {
    "name": "frozen",
    "trans": [],
    "usphone": "",
    "ukphone": ""
  },
  {
    "name": "Chilean",
    "trans": [],
    "usphone": "",
    "ukphone": ""
  },
  {
    "name": "sail",
    "trans": [],
    "usphone": "",
    "ukphone": ""
  },
  {
    "name": "continent",
    "trans": [],
    "usphone": "",
    "ukphone": ""
  },
  {
    "name": "bury",
    "trans": [],
    "usphone": "",
    "ukphone": ""
  },
  {
    "name": "exceptional",
    "trans": [],
    "usphone": "",
    "ukphone": ""
  },
  {
    "name": "leadership",
    "trans": [],
    "usphone": "",
    "ukphone": ""
  },
  {
    "name": "unbelievable",
    "trans": [],
    "usphone": "",
    "ukphone": ""
  },
  {
    "name": "set out",
    "trans": [],
    "usphone": "",
    "ukphone": ""
  },
  {
    "name": "the Endurance",
    "trans": [],
    "usphone": "",
    "ukphone": ""
  },
  {
    "name": "Antarctica",
    "trans": [],
    "usphone": "",
    "ukphone": ""
  },
  {
    "name": "the South Pole",
    "trans": [],
    "usphone": "",
    "ukphone": ""
  },
  {
    "name": "Elephant Island",
    "trans": [],
    "usphone": "",
    "ukphone": ""
  },
  {
    "name": "voyage",
    "trans": [],
    "usphone": "",
    "ukphone": ""
  },
  {
    "name": "impression",
    "trans": [],
    "usphone": "",
    "ukphone": ""
  },
  {
    "name": "sailor",
    "trans": [],
    "usphone": "",
    "ukphone": ""
  },
  {
    "name": "dive",
    "trans": [],
    "usphone": "",
    "ukphone": ""
  },
  {
    "name": "depth",
    "trans": [],
    "usphone": "",
    "ukphone": ""
  },
  {
    "name": "resolution",
    "trans": [],
    "usphone": "",
    "ukphone": ""
  },
  {
    "name": "resolve",
    "trans": [],
    "usphone": "",
    "ukphone": ""
  },
  {
    "name": "desperate",
    "trans": [],
    "usphone": "",
    "ukphone": ""
  },
  {
    "name": "plainly",
    "trans": [],
    "usphone": "",
    "ukphone": ""
  },
  {
    "name": "soundness",
    "trans": [],
    "usphone": "",
    "ukphone": ""
  },
  {
    "name": "observation",
    "trans": [],
    "usphone": "",
    "ukphone": ""
  },
  {
    "name": "expose",
    "trans": [],
    "usphone": "",
    "ukphone": ""
  },
  {
    "name": "shore",
    "trans": [],
    "usphone": "",
    "ukphone": ""
  },
  {
    "name": "last",
    "trans": [],
    "usphone": "",
    "ukphone": ""
  },
  {
    "name": "indeed",
    "trans": [],
    "usphone": "",
    "ukphone": ""
  },
  {
    "name": "afterwards",
    "trans": [],
    "usphone": "",
    "ukphone": ""
  },
  {
    "name": "calm",
    "trans": [],
    "usphone": "",
    "ukphone": ""
  },
  {
    "name": "sea-sick",
    "trans": [],
    "usphone": "",
    "ukphone": ""
  },
  {
    "name": "charming",
    "trans": [],
    "usphone": "",
    "ukphone": ""
  },
  {
    "name": "perfectly",
    "trans": [],
    "usphone": "",
    "ukphone": ""
  },
  {
    "name": "rough",
    "trans": [],
    "usphone": "",
    "ukphone": ""
  },
  {
    "name": "persuade",
    "trans": [],
    "usphone": "",
    "ukphone": ""
  },
  {
    "name": "clap",
    "trans": [],
    "usphone": "",
    "ukphone": ""
  },
  {
    "name": "frightened",
    "trans": [],
    "usphone": "",
    "ukphone": ""
  },
  {
    "name": "freshwater",
    "trans": [],
    "usphone": "",
    "ukphone": ""
  },
  {
    "name": "clear up",
    "trans": [],
    "usphone": "",
    "ukphone": ""
  },
  {
    "name": "die away",
    "trans": [],
    "usphone": "",
    "ukphone": ""
  },
  {
    "name": "come up",
    "trans": [],
    "usphone": "",
    "ukphone": ""
  },
  {
    "name": "dome",
    "trans": [],
    "usphone": "",
    "ukphone": ""
  },
  {
    "name": "proof",
    "trans": [],
    "usphone": "",
    "ukphone": ""
  },
  {
    "name": "solar-powered",
    "trans": [],
    "usphone": "",
    "ukphone": ""
  },
  {
    "name": "dust",
    "trans": [],
    "usphone": "",
    "ukphone": ""
  },
  {
    "name": "iron",
    "trans": [],
    "usphone": "",
    "ukphone": ""
  },
  {
    "name": "energy",
    "trans": [],
    "usphone": "",
    "ukphone": ""
  },
  {
    "name": "equivalent",
    "trans": [],
    "usphone": "",
    "ukphone": ""
  },
  {
    "name": "ring",
    "trans": [],
    "usphone": "",
    "ukphone": ""
  },
  {
    "name": "ski",
    "trans": [],
    "usphone": "",
    "ukphone": ""
  },
  {
    "name": "nestle",
    "trans": [],
    "usphone": "",
    "ukphone": ""
  },
  {
    "name": "gigantic",
    "trans": [],
    "usphone": "",
    "ukphone": ""
  },
  {
    "name": "surround",
    "trans": [],
    "usphone": "",
    "ukphone": ""
  },
  {
    "name": "lush",
    "trans": [],
    "usphone": "",
    "ukphone": ""
  },
  {
    "name": "shrub",
    "trans": [],
    "usphone": "",
    "ukphone": ""
  },
  {
    "name": "flit",
    "trans": [],
    "usphone": "",
    "ukphone": ""
  },
  {
    "name": "roof-top",
    "trans": [],
    "usphone": "",
    "ukphone": ""
  },
  {
    "name": "constant",
    "trans": [],
    "usphone": "",
    "ukphone": ""
  },
  {
    "name": "loft",
    "trans": [],
    "usphone": "",
    "ukphone": ""
  },
  {
    "name": "roof",
    "trans": [],
    "usphone": "",
    "ukphone": ""
  },
  {
    "name": "border",
    "trans": [],
    "usphone": "",
    "ukphone": ""
  },
  {
    "name": "lawn",
    "trans": [],
    "usphone": "",
    "ukphone": ""
  },
  {
    "name": "normally",
    "trans": [],
    "usphone": "",
    "ukphone": ""
  },
  {
    "name": "fancy",
    "trans": [],
    "usphone": "",
    "ukphone": ""
  },
  {
    "name": "solar panel",
    "trans": [],
    "usphone": "",
    "ukphone": ""
  },
  {
    "name": "space-age",
    "trans": [],
    "usphone": "",
    "ukphone": ""
  },
  {
    "name": "butler",
    "trans": [],
    "usphone": "",
    "ukphone": ""
  },
  {
    "name": "oversee",
    "trans": [],
    "usphone": "",
    "ukphone": ""
  },
  {
    "name": "security",
    "trans": [],
    "usphone": "",
    "ukphone": ""
  },
  {
    "name": "discreet",
    "trans": [],
    "usphone": "",
    "ukphone": ""
  },
  {
    "name": "servant",
    "trans": [],
    "usphone": "",
    "ukphone": ""
  },
  {
    "name": "humidity",
    "trans": [],
    "usphone": "",
    "ukphone": ""
  },
  {
    "name": "lighting",
    "trans": [],
    "usphone": "",
    "ukphone": ""
  },
  {
    "name": "gadget",
    "trans": [],
    "usphone": "",
    "ukphone": ""
  },
  {
    "name": "chore",
    "trans": [],
    "usphone": "",
    "ukphone": ""
  },
  {
    "name": "crossword",
    "trans": [],
    "usphone": "",
    "ukphone": ""
  },
  {
    "name": "button",
    "trans": [],
    "usphone": "",
    "ukphone": ""
  },
  {
    "name": "forwards",
    "trans": [],
    "usphone": "",
    "ukphone": ""
  },
  {
    "name": "integrated",
    "trans": [],
    "usphone": "",
    "ukphone": ""
  },
  {
    "name": "laundry",
    "trans": [],
    "usphone": "",
    "ukphone": ""
  },
  {
    "name": "easy-care",
    "trans": [],
    "usphone": "",
    "ukphone": ""
  },
  {
    "name": "fabric",
    "trans": [],
    "usphone": "",
    "ukphone": ""
  },
  {
    "name": "socket",
    "trans": [],
    "usphone": "",
    "ukphone": ""
  },
  {
    "name": "attach",
    "trans": [],
    "usphone": "",
    "ukphone": ""
  },
  {
    "name": "electrical",
    "trans": [],
    "usphone": "",
    "ukphone": ""
  },
  {
    "name": "appliance",
    "trans": [],
    "usphone": "",
    "ukphone": ""
  },
  {
    "name": "old-fashioned",
    "trans": [],
    "usphone": "",
    "ukphone": ""
  },
  {
    "name": "duster",
    "trans": [],
    "usphone": "",
    "ukphone": ""
  },
  {
    "name": "filter",
    "trans": [],
    "usphone": "",
    "ukphone": ""
  },
  {
    "name": "scent",
    "trans": [],
    "usphone": "",
    "ukphone": ""
  },
  {
    "name": "perfume",
    "trans": [],
    "usphone": "",
    "ukphone": ""
  },
  {
    "name": "entrance",
    "trans": [],
    "usphone": "",
    "ukphone": ""
  },
  {
    "name": "adventure",
    "trans": [],
    "usphone": "",
    "ukphone": ""
  },
  {
    "name": "simulator",
    "trans": [],
    "usphone": "",
    "ukphone": ""
  },
  {
    "name": "surfing",
    "trans": [],
    "usphone": "",
    "ukphone": ""
  },
  {
    "name": "loathe",
    "trans": [],
    "usphone": "",
    "ukphone": ""
  },
  {
    "name": "for a start",
    "trans": [],
    "usphone": "",
    "ukphone": ""
  },
  {
    "name": "on your way",
    "trans": [],
    "usphone": "",
    "ukphone": ""
  },
  {
    "name": "on the way",
    "trans": [],
    "usphone": "",
    "ukphone": ""
  },
  {
    "name": "on its way",
    "trans": [],
    "usphone": "",
    "ukphone": ""
  },
  {
    "name": "automatically",
    "trans": [],
    "usphone": "",
    "ukphone": ""
  },
  {
    "name": "wardrobe",
    "trans": [],
    "usphone": "",
    "ukphone": ""
  },
  {
    "name": "housekeeper",
    "trans": [],
    "usphone": "",
    "ukphone": ""
  },
  {
    "name": "nanny",
    "trans": [],
    "usphone": "",
    "ukphone": ""
  },
  {
    "name": "advertise",
    "trans": [],
    "usphone": "",
    "ukphone": ""
  },
  {
    "name": "reliable",
    "trans": [],
    "usphone": "",
    "ukphone": ""
  },
  {
    "name": "quantity",
    "trans": [],
    "usphone": "",
    "ukphone": ""
  },
  {
    "name": "overpopulation",
    "trans": [],
    "usphone": "",
    "ukphone": ""
  },
  {
    "name": "room",
    "trans": [],
    "usphone": "",
    "ukphone": ""
  },
  {
    "name": "error",
    "trans": [],
    "usphone": "",
    "ukphone": ""
  },
  {
    "name": "interconnect",
    "trans": [],
    "usphone": "",
    "ukphone": ""
  },
  {
    "name": "tunnel",
    "trans": [],
    "usphone": "",
    "ukphone": ""
  },
  {
    "name": "skyscraper",
    "trans": [],
    "usphone": "",
    "ukphone": ""
  },
  {
    "name": "identical",
    "trans": [],
    "usphone": "",
    "ukphone": ""
  },
  {
    "name": "spot",
    "trans": [],
    "usphone": "",
    "ukphone": ""
  },
  {
    "name": "lecturer",
    "trans": [],
    "usphone": "",
    "ukphone": ""
  },
  {
    "name": "polar bear",
    "trans": [],
    "usphone": "",
    "ukphone": ""
  },
  {
    "name": "tap",
    "trans": [],
    "usphone": "",
    "ukphone": ""
  },
  {
    "name": "metallic",
    "trans": [],
    "usphone": "",
    "ukphone": ""
  },
  {
    "name": "echo",
    "trans": [],
    "usphone": "",
    "ukphone": ""
  },
  {
    "name": "recycle",
    "trans": [],
    "usphone": "",
    "ukphone": ""
  },
  {
    "name": "take over from",
    "trans": [],
    "usphone": "",
    "ukphone": ""
  },
  {
    "name": "nap",
    "trans": [],
    "usphone": "",
    "ukphone": ""
  },
  {
    "name": "hike",
    "trans": [],
    "usphone": "",
    "ukphone": ""
  },
  {
    "name": "benefit",
    "trans": [],
    "usphone": "",
    "ukphone": ""
  },
  {
    "name": "adventurous",
    "trans": [],
    "usphone": "",
    "ukphone": ""
  },
  {
    "name": "sustainable",
    "trans": [],
    "usphone": "",
    "ukphone": ""
  },
  {
    "name": "base",
    "trans": [],
    "usphone": "",
    "ukphone": ""
  },
  {
    "name": "exhaust",
    "trans": [],
    "usphone": "",
    "ukphone": ""
  },
  {
    "name": "wilderness",
    "trans": [],
    "usphone": "",
    "ukphone": ""
  },
  {
    "name": "badge",
    "trans": [],
    "usphone": "",
    "ukphone": ""
  },
  {
    "name": "pin",
    "trans": [],
    "usphone": "",
    "ukphone": ""
  },
  {
    "name": "explore",
    "trans": [],
    "usphone": "",
    "ukphone": ""
  },
  {
    "name": "ocean",
    "trans": [],
    "usphone": "",
    "ukphone": ""
  },
  {
    "name": "adventurer",
    "trans": [],
    "usphone": "",
    "ukphone": ""
  },
  {
    "name": "closet",
    "trans": [],
    "usphone": "",
    "ukphone": ""
  },
  {
    "name": "on the road",
    "trans": [],
    "usphone": "",
    "ukphone": ""
  },
  {
    "name": "go on to",
    "trans": [],
    "usphone": "",
    "ukphone": ""
  },
  {
    "name": "substantial",
    "trans": [],
    "usphone": "",
    "ukphone": ""
  },
  {
    "name": "forehead",
    "trans": [],
    "usphone": "",
    "ukphone": ""
  },
  {
    "name": "altogether",
    "trans": [],
    "usphone": "",
    "ukphone": ""
  },
  {
    "name": "in the course of",
    "trans": [],
    "usphone": "",
    "ukphone": ""
  },
  {
    "name": "over the course of",
    "trans": [],
    "usphone": "",
    "ukphone": ""
  }
]